setup.py
gnb_distributions_lite/Binomialdistribution.py
gnb_distributions_lite/Gaussiandistribution.py
gnb_distributions_lite/Generaldistribution.py
gnb_distributions_lite/__init__.py
gnb_distributions_lite.egg-info/PKG-INFO
gnb_distributions_lite.egg-info/SOURCES.txt
gnb_distributions_lite.egg-info/dependency_links.txt
gnb_distributions_lite.egg-info/not-zip-safe
gnb_distributions_lite.egg-info/top_level.txt